rsokl_dummy/__init__.py
rsokl_dummy/_version.py
rsokl_dummy/basic_functions.py
rsokl_dummy/numpy_functions.py
rsokl_dummy-0.1.2.dist-info/METADATA
rsokl_dummy-0.1.2.dist-info/WHEEL
rsokl_dummy-0.1.2.dist-info/top_level.txt
rsokl_dummy-0.1.2.dist-info/RECORD
