Metadata-Version: 2.1
Name: rsokl-dummy
Version: 0.1.2
Summary: A dummy repo for testing CI/CD automation.
Home-page: https://github.com/rsokl/Dummy_Repo
Author: Ryan Soklaski
Author-email: rsoklaski@gmail.com
License: MIT
Download-URL: https://github.com/rsokl/rsokl_dummy/tarball/0.1.2
Platform: UNKNOWN
Requires-Python: >=3.6
Requires-Dist: numpy (<=1.19.3,>=1.12)
